llama_index/packs/streamlit_chatbot/__init__.py
llama_index/packs/streamlit_chatbot/base.py
llama_index_packs_streamlit_chatbot-0.5.2.dist-info/METADATA
llama_index_packs_streamlit_chatbot-0.5.2.dist-info/WHEEL
llama_index_packs_streamlit_chatbot-0.5.2.dist-info/licenses/LICENSE
llama_index_packs_streamlit_chatbot-0.5.2.dist-info/RECORD
