Metadata-Version: 2.4
Name: llama-index-packs-streamlit-chatbot
Version: 0.5.2
Summary: llama-index packs streamlit_chatbot integration
Author-email: Your Name <you@example.com>
Maintainer: carolinedlu
License-Expression: MIT
License-File: LICENSE
Keywords: chatbot,snowflake,streamlit,wikipedia
Requires-Python: >=3.9
Requires-Dist: llama-index-core<0.15,>=0.13.0
Requires-Dist: llama-index-llms-openai<0.6,>=0.5.0
Requires-Dist: llama-index-readers-wikipedia<0.5,>=0.4.0
Requires-Dist: streamlit-pills<0.4,>=0.3.0
Requires-Dist: streamlit<2,>=1.30.0
Requires-Dist: wikipedia<2,>=1.4.0
